[
  {
    "params": {},
    "results": [
      {
        "instance": 6,
        "results": {
          "C_max": 7105.0,
          "order": [
            56,
            79,
            94,
            87,
            84,
            92,
            61,
            97,
            48,
            90,
            26,
            59,
            95,
            51,
            40,
            66,
            1,
            13,
            44,
            50,
            72,
            93,
            0,
            29,
            18,
            32,
            58,
            19,
            22,
            47,
            30,
            12,
            33,
            42,
            71,
            6,
            83,
            96,
            10,
            5,
            15,
            88,
            28,
            41,
            76,
            81,
            68,
            11,
            54,
            7,
            60,
            35,
            89,
            46,
            52,
            20,
            86,
            16,
            17,
            73,
            23,
            38,
            57,
            78,
            39,
            98,
            31,
            53,
            91,
            62,
            70,
            55,
            63,
            45,
            14,
            99,
            69,
            9,
            3,
            65,
            8,
            25,
            2,
            34,
            64,
            21,
            36,
            49,
            37,
            27,
            85,
            4,
            43,
            80,
            82,
            24,
            77,
            67,
            75,
            74
          ],
          "time": 0.05966730000000009
        }
      }
    ]
  }
]