[
  {
    "params": {},
    "results": [
      {
        "instance": 7,
        "results": {
          "C_max": 2867.0,
          "order": [
            33,
            9,
            34,
            6,
            46,
            7,
            24,
            4,
            13,
            0,
            16,
            19,
            8,
            30,
            42,
            17,
            18,
            5,
            45,
            38,
            27,
            43,
            28,
            44,
            15,
            23,
            11,
            36,
            2,
            47,
            25,
            32,
            10,
            26,
            48,
            49,
            40,
            29,
            35,
            14,
            31,
            41,
            37,
            1,
            20,
            12,
            21,
            3,
            22,
            39
          ],
          "time": 0.0017225000000000712
        }
      }
    ]
  }
]